xtthread/__init__.py
xtthread/exception.py
xtthread/futures.py
xtthread/process.py
xtthread/production.py
xtthread/qthread.py
xtthread/singleton.py
xtthread/thread.py
xtthread/wraps.py
xtthread-0.0.7.dist-info/METADATA
xtthread-0.0.7.dist-info/WHEEL
xtthread-0.0.7.dist-info/top_level.txt
xtthread-0.0.7.dist-info/RECORD
