Metadata-Version: 2.4
Name: xtthread
Version: 0.0.7
Summary: 一个全面的Python并发编程增强库，为标准线程、进程和Qt线程提供了更高级的抽象和异常处理机制
Author-email: sandorn <sandorn@live.cn>
License: MIT
Project-URL: Homepage, https://github.com/sandorn/xtthread
Project-URL: Repository, https://github.com/sandorn/xtthread
Project-URL: Issues, https://github.com/sandorn/xtthread/issues
Keywords: thread,multithreading,multiprocessing,concurrency,parallelism,PyQt,async,futures
Classifier: Development Status :: 4 - Beta
Classifier: Intended Audience :: Developers
Classifier: License :: OSI Approved :: MIT License
Classifier: Programming Language :: Python :: 3.13
Classifier: Topic :: Software Development :: Libraries :: Python Modules
Classifier: Topic :: System :: Networking
Classifier: Topic :: System :: Distributed Computing
Requires-Python: >=3.13
Requires-Dist: psutil>=7.1.0
Requires-Dist: colorama>=0.4.6
Requires-Dist: loguru>=0.7.3
Requires-Dist: win32_setctime>=1.2.0
Provides-Extra: qt
Requires-Dist: PyQt6>=6.9.1; extra == "qt"
Requires-Dist: PyQt6-Qt6>=6.9.2; extra == "qt"
Requires-Dist: PyQt6_sip>=13.10.2; extra == "qt"
